{
    "extends": "dtslint/dt.json",
    "rules": {
        "array-type": false,
        "ban-types": false,
        "dt-header": false,
        "interface-name": false,
        "interface-over-type-literal": false,
        "max-line-length": false,
        "no-consecutive-blank-lines": false,
        "no-declare-current-package": false,
        "no-self-import": false,
        "no-unnecessary-class": false,
        "no-unnecessary-generics": false,
        "no-var-keyword": false,
        "npm-naming": false,
        "strict-export-declare-modifiers": false,
        "trim-file": false,
        "unified-signatures": false
    }
}
