{
    "extends": "@definitelytyped/dtslint/dt.json",
    "rules": {
        "ban-types": false,
        "no-consecutive-blank-lines": false,
        "no-padding": false,
        "no-var-keyword": false,
        "object-literal-shorthand": false,
        "only-arrow-functions": false,
        "semicolon": false,
        "space-before-function-paren": false,
        "space-within-parens": false,
        "strict-export-declare-modifiers": false,
        "trim-file": false,
        "unified-signatures": false
    }
}
